ailia_tokenizer/LICENSE_AILIA_EN.pdf
ailia_tokenizer/LICENSE_AILIA_JA.pdf
ailia_tokenizer/__init__.py
ailia_tokenizer/linux/arm64-v8a/libailia_tokenizer.so
ailia_tokenizer/linux/x64/libailia_tokenizer.so
ailia_tokenizer/mac/libailia_tokenizer.dylib
ailia_tokenizer/oss/LICENSE_MECAB.txt
ailia_tokenizer/oss/LICENSE_SENTENCEPIECE.txt
ailia_tokenizer/oss/LICENSE_SRELL.txt
ailia_tokenizer/windows/x64/ailia_tokenizer.dll
ailia_tokenizer-1.6.0.data/scripts/__init__.py
ailia_tokenizer-1.6.0.dist-info/METADATA
ailia_tokenizer-1.6.0.dist-info/WHEEL
ailia_tokenizer-1.6.0.dist-info/top_level.txt
ailia_tokenizer-1.6.0.dist-info/RECORD
