Metadata-Version: 2.4
Name: ailia_tokenizer
Version: 1.6.0
Summary: ailia Tokenizer
Home-page: https://ailia.ai/en/
Author: ailia Inc.
Author-email: contact@ailia.ai
License: https://ailia.ai/en/license/
Requires-Python: >3.6
Dynamic: author
Dynamic: author-email
Dynamic: description
Dynamic: description-content-type
Dynamic: home-page
Dynamic: license
Dynamic: requires-python
Dynamic: summary
